MANIFEST.in
README.md
setup.py
COGDumper.egg-info/PKG-INFO
COGDumper.egg-info/SOURCES.txt
COGDumper.egg-info/dependency_links.txt
COGDumper.egg-info/entry_points.txt
COGDumper.egg-info/requires.txt
COGDumper.egg-info/top_level.txt
cogdumper/__init__.py
cogdumper/cog_tiles.py
cogdumper/errors.py
cogdumper/filedumper.py
cogdumper/httpdumper.py
cogdumper/jpegreader.py
cogdumper/s3dumper.py
cogdumper/tifftags.py
cogdumper.egg-info/PKG-INFO
cogdumper.egg-info/SOURCES.txt
cogdumper.egg-info/dependency_links.txt
cogdumper.egg-info/entry_points.txt
cogdumper.egg-info/requires.txt
cogdumper.egg-info/top_level.txt
cogdumper/scripts/__init__.py
cogdumper/scripts/cli.py