Metadata-Version: 1.2
Name: cogdumper
Version: 1.1.0
Summary: UNKNOWN
Home-page: https://github.com/mapbox/COGDumper
Author: Norman Barker
Author-email: norman.barker@mapbox.com
License: MIT
Keywords: CloudOptimized Geotiff
Platform: UNKNOWN
Classifier: Intended Audience :: Information Technology
Classifier: Intended Audience :: Science/Research
Classifier: Programming Language :: Python :: 3.6
Classifier: Topic :: Scientific/Engineering :: GIS
Requires-Python: >=3
